README.md
setup.cfg
setup.py
dash_access/__init__.py
dash_access/create_tables.py
dash_access.egg-info/PKG-INFO
dash_access.egg-info/SOURCES.txt
dash_access.egg-info/dependency_links.txt
dash_access.egg-info/not-zip-safe
dash_access.egg-info/requires.txt
dash_access.egg-info/top_level.txt
dash_access/access/__init__.py
dash_access/access/control.py
dash_access/access/data.py
dash_access/access/group.py
dash_access/access/relationship.py
dash_access/access/relationship_objects.py
dash_access/access/user.py
dash_access/auth/__init__.py
dash_access/auth/auth.py
dash_access/auth/pw.py
dash_access/clients/__init__.py
dash_access/clients/base.py
dash_access/clients/dynamo.py
dash_access/clients/mysql.py
dash_access/clients/postgres.py
dash_access/clients/sqlite3.py
dash_access/utils/__init__.py
dash_access/utils/dev_utils.py